{"head": "ba014111add5deeedd48b27fb33e3a41938f9420", "file_count": 9, "files": [{"path": ".tars/context.md", "size": 1459}, {"path": "README.md", "size": 575}, {"path": "index.html", "size": 1027}, {"path": "package.json", "size": 483}, {"path": "test/__tests__/smoke-test.spec.ts", "size": 1754}, {"path": "test/config.yml", "size": 207}, {"path": "test/results.log", "size": 0}, {"path": "test/smoke-test.ts", "size": 4750}, {"path": "tsconfig.json", "size": 197}], "symbols": {"test/smoke-test.ts": ["Config", "TestResult", "configPath", "loadConfig", "log", "error", "startServer", "stopServer", "setupBrowser", "teardownBrowser", "runTests", "reportResults", "main"], "test/__tests__/smoke-test.spec.ts": ["mockLoadConfig", "mockRunTests"]}, "readme_head": "# tars-test\n\nA simple demonstration project showcasing the integration of TARS, an AI assistant for software development and business.\n\n## Running Locally\n1. Clone the repository:\n   ```bash\ngit clone https://github.com/dsneed123/tars-test.git\ncd tars-test\n```\n2. Install dependencies:\n   ```bash\nnpm install\n```\n3. Run the smoke test:\n   ```bash\nnpm run smoke-test\n```\n\n## Testing\n- The project includes a CLI-based smoke test suite that validates HTML page loading, TARS integration functionality, and interactive elements.\n- Test results are logged to `test/results.log`.\n"}